LICENSE-APACHE
LICENSE-MIT
MANIFEST.in
NOTICE
README.md
setup.py
smeagle/__init__.py
smeagle/loader.py
smeagle/logger.py
smeagle/version.py
smeagle.egg-info/PKG-INFO
smeagle.egg-info/SOURCES.txt
smeagle.egg-info/dependency_links.txt
smeagle.egg-info/not-zip-safe
smeagle.egg-info/requires.txt
smeagle.egg-info/top_level.txt
smeagle/backends/__init__.py
smeagle/backends/corpus.py
smeagle/backends/elf/__init__.py
smeagle/backends/elf/corpus.py
smeagle/backends/elf/decorator.py
smeagle/backends/elf/elf.py
smeagle/backends/elf/location.py
smeagle/backends/elf/types.py
smeagle/backends/elf/variable_type.py
smeagle/backends/elf/parser/__init__.py
smeagle/backends/elf/parser/AMD64/__init__.py
smeagle/backends/elf/parser/AMD64/allocators.py
smeagle/backends/elf/parser/AMD64/classifier.py
smeagle/backends/elf/parser/AMD64/register_class.py