Metadata-Version: 2.1
Name: smeagle
Version: 0.0.12
Summary: Fact generation for elf binaries with debug
Home-page: https://github.com/buildsi/smeagle-py
Author: Vanessa Sochat
Author-email: vsoch@users.noreply.github.com
Maintainer: Vanessa Sochat
License: LICENSE
Keywords: ELF,DWARF,binary metadata
Platform: UNKNOWN
Classifier: Intended Audience :: Science/Research
Classifier: Intended Audience :: Developers
Classifier: License :: OSI Approved :: Mozilla Public License 2.0 (MPL 2.0)
Classifier: Programming Language :: C
Classifier: Programming Language :: Python
Classifier: Topic :: Software Development
Classifier: Topic :: Scientific/Engineering
Classifier: Operating System :: Unix
Classifier: Programming Language :: Python :: 3.7
Provides-Extra: all
License-File: LICENSE-APACHE
License-File: LICENSE-MIT
License-File: NOTICE
